{"textures":{"0":"modelengine:entity/soul_minion","particle":"#0"},"elements":[{"from":[7.4458303,3.9583302,6.5],"to":[9.69583,8.95833,9.5],"faces":{"east":{"uv":[10.0,6.75,9.25,8.0],"tintindex":0,"rotation":0,"texture":"#0"},"south":{"uv":[9.25,9.75,8.75,11.0],"tintindex":0,"rotation":0,"texture":"#0"},"north":{"uv":[8.75,9.75,8.25,11.0],"tintindex":0,"rotation":0,"texture":"#0"},"west":{"uv":[10.0,5.5,9.25,6.75],"tintindex":0,"rotation":0,"texture":"#0"},"up":{"uv":[9.75,10.75,10.25,10.0],"tintindex":0,"rotation":0,"texture":"#0"},"down":{"uv":[1.25,10.25,1.75,11.0],"tintindex":0,"rotation":0,"texture":"#0"}}},{"from":[8.44583,4.45833,9.0],"to":[9.44583,6.95833,10.0],"faces":{"east":{"uv":[8.0,11.25,7.75,12.0],"tintindex":0,"rotation":0,"texture":"#0"},"south":{"uv":[7.75,11.25,7.5,12.0],"tintindex":0,"rotation":0,"texture":"#0"},"north":{"uv":[7.25,11.25,7.0,12.0],"tintindex":0,"rotation":0,"texture":"#0"},"west":{"uv":[7.5,11.25,7.25,12.0],"tintindex":0,"rotation":0,"texture":"#0"},"up":{"uv":[11.0,3.0,11.25,2.75],"tintindex":0,"rotation":0,"texture":"#0"},"down":{"uv":[11.0,11.5,11.25,11.75],"tintindex":0,"rotation":0,"texture":"#0"}}},{"from":[8.44583,3.4583302,6.0],"to":[9.44583,4.45833,10.0],"faces":{"east":{"uv":[9.25,4.0,8.25,4.25],"tintindex":0,"rotation":0,"texture":"#0"},"south":{"uv":[3.25,6.75,3.0,7.0],"tintindex":0,"rotation":0,"texture":"#0"},"north":{"uv":[5.5,3.25,5.25,3.5],"tintindex":0,"rotation":0,"texture":"#0"},"west":{"uv":[5.25,3.25,4.25,3.5],"tintindex":0,"rotation":0,"texture":"#0"},"up":{"uv":[9.75,11.75,10.0,10.75],"tintindex":0,"rotation":0,"texture":"#0"},"down":{"uv":[10.0,10.75,10.25,11.75],"tintindex":0,"rotation":0,"texture":"#0"}}},{"from":[9.44583,3.4583302,6.0],"to":[10.19583,6.95833,10.0],"faces":{"east":{"uv":[2.25,9.25,1.25,10.25],"tintindex":0,"rotation":0,"texture":"#0"},"south":{"uv":[5.5,10.75,5.25,11.75],"tintindex":0,"rotation":0,"texture":"#0"},"north":{"uv":[5.25,10.75,5.0,11.75],"tintindex":0,"rotation":0,"texture":"#0"},"west":{"uv":[9.25,8.75,8.25,9.75],"tintindex":0,"rotation":0,"texture":"#0"},"up":{"uv":[9.25,11.75,9.5,10.75],"tintindex":0,"rotation":0,"texture":"#0"},"down":{"uv":[9.5,10.75,9.75,11.75],"tintindex":0,"rotation":0,"texture":"#0"}}},{"from":[7.34583,8.45833,6.0],"to":[10.19583,9.45833,10.0],"faces":{"east":{"uv":[11.5,7.5,10.5,7.75],"tintindex":0,"rotation":0,"texture":"#0"},"south":{"uv":[11.5,4.75,10.75,5.0],"tintindex":0,"rotation":0,"texture":"#0"},"north":{"uv":[4.0,5.0,3.25,5.25],"tintindex":0,"rotation":0,"texture":"#0"},"west":{"uv":[11.5,1.5,10.5,1.75],"tintindex":0,"rotation":0,"texture":"#0"},"up":{"uv":[9.75,1.75,10.5,0.75],"tintindex":0,"rotation":0,"texture":"#0"},"down":{"uv":[9.75,8.0,10.5,9.0],"tintindex":0,"rotation":0,"texture":"#0"}}},{"from":[8.44583,4.45833,6.0],"to":[9.44583,6.95833,7.0],"faces":{"east":{"uv":[5.0,11.25,4.75,12.0],"tintindex":0,"rotation":0,"texture":"#0"},"south":{"uv":[1.25,11.25,1.0,12.0],"tintindex":0,"rotation":0,"texture":"#0"},"north":{"uv":[0.75,10.0,0.5,10.75],"tintindex":0,"rotation":0,"texture":"#0"},"west":{"uv":[6.25,11.0,6.0,11.75],"tintindex":0,"rotation":0,"texture":"#0"},"up":{"uv":[2.75,8.25,3.0,8.0],"tintindex":0,"rotation":0,"texture":"#0"},"down":{"uv":[5.5,10.25,5.75,10.5],"tintindex":0,"rotation":0,"texture":"#0"}}}],"display":{"gui":{"rotation":[-150.0,-45.0,180.0]}}}